rtfunicode/__init__.py
rtfunicode/py.typed
rtfunicode-2.3.dist-info/licenses/LICENSE.txt
rtfunicode-2.3.dist-info/WHEEL
rtfunicode-2.3.dist-info/METADATA
rtfunicode-2.3.dist-info/RECORD
