Metadata-Version: 2.4
Name: rtfunicode
Version: 2.3
Summary: Encoder for unicode to RTF 1.5 command sequences
Keywords: rtf
Author: Martijn Pieters
Author-email: Martijn Pieters <mj@zopatista.com>
License-Expression: BSD-2-Clause
License-File: LICENSE.txt
Classifier: Development Status :: 5 - Production/Stable
Classifier: Intended Audience :: Developers
Classifier: License :: OSI Approved :: BSD License
Classifier: Programming Language :: Python :: 3
Requires-Python: >=3.10
Project-URL: Homepage, https://github.com/mjpieters/rtfunicode
Project-URL: Repository, https://github.com/mjpieters/rtfunicode
Project-URL: Issues, https://github.com/mjpieters/rtfunicode/issues
Project-URL: Changelog, https://github.com/mjpieters/rtfunicode/blob/main/CHANGELOG.md
